odbcdol/__init__.py
odbcdol/tests/__init__.py
odbcdol/tests/test_simple.py
odbcdol-0.0.3.dist-info/LICENSE
odbcdol-0.0.3.dist-info/METADATA
odbcdol-0.0.3.dist-info/WHEEL
odbcdol-0.0.3.dist-info/top_level.txt
odbcdol-0.0.3.dist-info/RECORD
